odoo/addons/shopfloor_checkout_sync/README.rst
odoo/addons/shopfloor_checkout_sync/__init__.py
odoo/addons/shopfloor_checkout_sync/__manifest__.py
odoo/addons/shopfloor_checkout_sync/actions/__init__.py
odoo/addons/shopfloor_checkout_sync/actions/checkout_sync.py
odoo/addons/shopfloor_checkout_sync/actions/stock.py
odoo/addons/shopfloor_checkout_sync/i18n/es_AR.po
odoo/addons/shopfloor_checkout_sync/i18n/it.po
odoo/addons/shopfloor_checkout_sync/i18n/shopfloor_checkout_sync.pot
odoo/addons/shopfloor_checkout_sync/readme/CONTRIBUTORS.rst
odoo/addons/shopfloor_checkout_sync/readme/CREDITS.rst
odoo/addons/shopfloor_checkout_sync/readme/DESCRIPTION.rst
odoo/addons/shopfloor_checkout_sync/static/description/icon.png
odoo/addons/shopfloor_checkout_sync/static/description/index.html
odoo/addons/shopfloor_checkout_sync/tests/__init__.py
odoo/addons/shopfloor_checkout_sync/tests/common.py
odoo/addons/shopfloor_checkout_sync/tests/test_shopfloor_cluster_picking_sync.py
odoo/addons/shopfloor_checkout_sync/tests/test_shopfloor_location_content_transfer_sync.py
odoo/addons/shopfloor_checkout_sync/tests/test_shopfloor_zone_picking_sync.py
odoo14_addon_shopfloor_checkout_sync-14.0.1.3.0.dist-info/METADATA
odoo14_addon_shopfloor_checkout_sync-14.0.1.3.0.dist-info/WHEEL
odoo14_addon_shopfloor_checkout_sync-14.0.1.3.0.dist-info/top_level.txt
odoo14_addon_shopfloor_checkout_sync-14.0.1.3.0.dist-info/RECORD
